MANIFEST.in
README.md
pyproject.toml
setup.cfg
setup.py
bioel/__init__.py
bioel/dataset.py
bioel/evaluate.py
bioel/linking_eval.py
bioel/logger.py
bioel/model.py
bioel/ontology.py
bioel.egg-info/PKG-INFO
bioel.egg-info/SOURCES.txt
bioel.egg-info/dependency_links.txt
bioel.egg-info/not-zip-safe
bioel.egg-info/requires.txt
bioel.egg-info/top_level.txt
bioel/models/__init__.py
bioel/models/arboel/__init__.py
bioel/models/arboel/Crossencoder/__init__.py
bioel/models/arboel/Crossencoder/crossencoder.py
bioel/models/arboel/Crossencoder/eeval_cluster_linking.py
bioel/models/arboel/Crossencoder/train_crossencoder_mst.py
bioel/models/arboel/Crossencoder/original/__init__.py
bioel/models/arboel/Crossencoder/original/crossencoder.py
bioel/models/arboel/Crossencoder/original/data_process.py
bioel/models/arboel/Crossencoder/original/evaluate_crossencoder.py
bioel/models/arboel/Crossencoder/original/my_train_cross.py
bioel/models/arboel/Crossencoder/original/train_cross.py
bioel/models/arboel/biencoder/__init__.py
bioel/models/arboel/biencoder/evaluate_biencoder.py
bioel/models/arboel/biencoder/train_biencoder.py
bioel/models/arboel/biencoder/data/BiEncoderLightningDataModule.py
bioel/models/arboel/biencoder/data/__init__.py
bioel/models/arboel/biencoder/data/data_process.py
bioel/models/arboel/biencoder/data/data_utils.py
bioel/models/arboel/biencoder/model/BiEncoderLightningModule.py
bioel/models/arboel/biencoder/model/__init__.py
bioel/models/arboel/biencoder/model/biencoder.py
bioel/models/arboel/biencoder/model/eval_biencoder.py
bioel/models/arboel/biencoder/model/eval_cluster_linking.py
bioel/models/arboel/biencoder/model/common/__init__.py
bioel/models/arboel/biencoder/model/common/optimizer.py
bioel/models/arboel/biencoder/model/common/params.py
bioel/models/arboel/biencoder/model/common/ranker_base.py
bioel/models/arboel/biencoder/model/special_partition/special_partition.c
bioel/models/arboel/biencoder/model/special_partition/special_partition.pyx
bioel/models/arboel/crossencoder/__init__.py
bioel/models/arboel/crossencoder/evaluate_crossencoder.py
bioel/models/arboel/crossencoder/train_crossencoder.py
