Metadata-Version: 2.2
Name: bioel
Version: 0.1.11
Summary: An easy-to-use package for all your biomedical entity linking needs.
Home-page: https://github.com/davidkartchner/biomedical-entity-linking/tree/main/bioel
Author: Pathology Dynamics Lab, Georgia Institute of Technology
Author-email: 
License: MIT
Keywords: bioel,biomedical,entity,linking,entity-linking,biomedical-entity-linking
Requires-Python: >=3.9
Requires-Dist: pytest
Requires-Dist: tqdm
Requires-Dist: pandas
Requires-Dist: numpy
Requires-Dist: matplotlib
Requires-Dist: seaborn
Requires-Dist: obonet
Requires-Dist: datasets
Requires-Dist: ujson
Requires-Dist: bioc
Requires-Dist: logger
Requires-Dist: lightning
Requires-Dist: ipython
Requires-Dist: cython
Requires-Dist: transformers==4.44.2
Requires-Dist: pytorch_transformers
Requires-Dist: scipy
Requires-Dist: faiss-gpu
Requires-Dist: faiss-cpu
Requires-Dist: wandb
Requires-Dist: scikit-learn
Requires-Dist: torch==2.4
Requires-Dist: scispacy
Requires-Dist: accelerate
Requires-Dist: pytorch_metric_learning
Dynamic: author
Dynamic: description
Dynamic: description-content-type
Dynamic: home-page
Dynamic: keywords
Dynamic: license
Dynamic: requires-dist
Dynamic: requires-python
Dynamic: summary
